Metadata-Version: 1.0
Name: quotes-wrapper
Version: 0.0.5
Summary: Just Another API Wrapper
Home-page: https://bitbucket.org/ematos/quotes-wrapper
Author: Eduardo Matos
Author-email: eduardo.matos.silva@gmail.com
License: UNKNOWN
Platform: UNKNOWN
